authly_sdk/__init__.py
authly_sdk/client.py
authly_sdk/client.pyi
authly_sdk/config.py
authly_sdk/config.pyi
authly_sdk/exceptions.py
authly_sdk/exceptions.pyi
authly_sdk/py.typed
authly_sdk/schemas/__init__.py
authly_sdk/schemas/claims.py
authly_sdk/tokens/__init__.py
authly_sdk/tokens/__init__.pyi
authly_sdk/tokens/verifier.py
authly_sdk/tokens/verifier.pyi
authly_sdk/types/__init__.py
authly_sdk/types/__init__.pyi
authly_sdk/types/claims.py
authly_sdk/types/claims.pyi
authly_sdk-0.1.4.dist-info/METADATA
authly_sdk-0.1.4.dist-info/WHEEL
authly_sdk-0.1.4.dist-info/licenses/LICENSE
authly_sdk-0.1.4.dist-info/RECORD
