Metadata-Version: 2.4
Name: authly-sdk
Version: 0.1.4
Summary: A library for building authentication systems using Authly.
Author-email: zeediv <hello@zdv.sh>
License: MIT License
License-File: LICENSE
Requires-Python: >=3.12
Requires-Dist: pyjwt>=2.10.1
